checkontap/__init__.py
checkontap/cli.py
checkontap/ontapcmd/__init__.py
checkontap/ontapcmd/about.py
checkontap/ontapcmd/aggregateusage.py
checkontap/ontapcmd/clusterhealth.py
checkontap/ontapcmd/diskhealth.py
checkontap/ontapcmd/hardwarehealth.py
checkontap/ontapcmd/interfacehealth.py
checkontap/ontapcmd/lunusage.py
checkontap/ontapcmd/porthealth.py
checkontap/ontapcmd/snapmirrorhealth.py
checkontap/ontapcmd/snapshothealth.py
checkontap/ontapcmd/volumehealth.py
checkontap/ontapcmd/volumeusage.py
checkontap/tools/__init__.py
checkontap/tools/cli.py
checkontap/tools/helper.py
checkontap-0.3.7.dist-info/entry_points.txt
checkontap-0.3.7.dist-info/licenses/LICENSE
checkontap-0.3.7.dist-info/WHEEL
checkontap-0.3.7.dist-info/METADATA
checkontap-0.3.7.dist-info/RECORD
