Metadata-Version: 2.4
Name: checkontap
Version: 0.3.7
Summary: check_ontap monitoring plugin
Author-email: Matthias Gallinger <matthias.gallinger@consol.de>
Requires-Python: >= 3.8
Classifier: Development Status :: 5 - Production/Stable
Classifier: Topic :: System :: Monitoring
Classifier: License :: OSI Approved :: GNU Affero General Public License v3 or later (AGPLv3+)
License-File: LICENSE
Requires-Dist: netapp-ontap >= 9.16.1.0
Requires-Dist: monplugin >= 0.6.3
Project-URL: homepage, https://github.com/Consol-Monitoring/check_ontap
Project-URL: issues, https://github.com/Consol-Monitoring/check_ontap/issues
Project-URL: repository, https://github.com/Consol-Monitoring/check_ontap.git
